jhub/__init__.py
jhub/_version.py
jhub/accelerators.py
jhub/defaults.py
jhub/io.py
jhub/mount.py
jhub/start.py
jhub/swarmspawner.py
jhub/util.py
jhub_swarmspawner-0.6.3.dist-info/licenses/LICENSE
jhub_swarmspawner-0.6.3.dist-info/METADATA
jhub_swarmspawner-0.6.3.dist-info/WHEEL
jhub_swarmspawner-0.6.3.dist-info/top_level.txt
jhub_swarmspawner-0.6.3.dist-info/RECORD
