Metadata-Version: 2.4
Name: jhub-swarmspawner
Version: 0.6.3
Summary: SwarmSpawner enables JupyterHub to spawn jupyter
Home-page: https://github.com/rasmunk/SwarmSpawner
Author: Rasmus Munk
Author-email: rasmus.munk@nbi.ku.dk
License: BSD
Keywords: Interactive,Interpreter,Shell,Web
Classifier: Development Status :: 4 - Beta
Classifier: Intended Audience :: Developers
Classifier: Topic :: Software Development :: Libraries :: Python Modules
Classifier: Programming Language :: Python :: 3.9
Classifier: Programming Language :: Python :: 3.10
Classifier: Programming Language :: Python :: 3.11
Classifier: Programming Language :: Python :: 3.12
License-File: LICENSE
Requires-Dist: docker>=7.0.0
Requires-Dist: jupyterhub>5.1.0
Requires-Dist: flatten_dict>=0.4.2
Requires-Dist: jhub-authenticators>=0.6.0
Requires-Dist: traitlets>=4.3.2
Requires-Dist: async_generator>=1.10.0
Provides-Extra: dev
Requires-Dist: docutils>=0.22.3; extra == "dev"
Requires-Dist: black>=25.12.0; extra == "dev"
Requires-Dist: flake8>=7.3.0; extra == "dev"
Provides-Extra: test
Requires-Dist: pytest==7.4.4; extra == "test"
Requires-Dist: docker==7.1.0; extra == "test"
Requires-Dist: docutils==0.21.2; extra == "test"
Requires-Dist: pygments==2.18.0; extra == "test"
Dynamic: author
Dynamic: author-email
Dynamic: classifier
Dynamic: description
Dynamic: home-page
Dynamic: keywords
Dynamic: license
Dynamic: license-file
Dynamic: provides-extra
Dynamic: requires-dist
Dynamic: summary
